lblprof/__init__.py
lblprof/curses_ui.py
lblprof/custom_sysmon.py
lblprof/line_stat_object.py
lblprof/line_stats_tree.py
lblprof-0.1.8.dist-info/METADATA
lblprof-0.1.8.dist-info/WHEEL
lblprof-0.1.8.dist-info/top_level.txt
lblprof-0.1.8.dist-info/RECORD
