Metadata-Version: 2.4
Name: lblprof
Version: 0.1.8
Summary: Line by line terminal based profiler
Author-email: le-codeur-rapide <paul.vezia@gmail.com>
License: MIT
Classifier: Programming Language :: Python :: 3
Classifier: License :: OSI Approved :: MIT License
Classifier: Operating System :: OS Independent
Requires-Python: >=3.12
Requires-Dist: pydantic>=2.0.0
Provides-Extra: dev
Requires-Dist: matplotlib>=3.10.1; extra == "dev"
Requires-Dist: virtualenv>=20.30.0; extra == "dev"
Requires-Dist: pandas>=2.0.3; extra == "dev"
Requires-Dist: chromadb>=0.5.23; extra == "dev"
Requires-Dist: ruff>=0.3.0; extra == "dev"
Requires-Dist: pytest>=7.0.0; extra == "dev"
Requires-Dist: black>=24.2.0; extra == "dev"
